mirnaprotpred/__init__.py
mirnaprotpred/SeqFinder/__init__.py
mirnaprotpred/SeqFinder/seqfinder.py
mirnaprotpred/SeqFinder/data/data.xlsx
mirnaprotpred/validator/__init__.py
mirnaprotpred/validator/validator.py
mirnaprotpred/validator/data/data.xlsx
mirnaprotpred-0.1.5.dist-info/licenses/LICENSE
mirnaprotpred-0.1.5.dist-info/METADATA
mirnaprotpred-0.1.5.dist-info/WHEEL
mirnaprotpred-0.1.5.dist-info/entry_points.txt
mirnaprotpred-0.1.5.dist-info/top_level.txt
mirnaprotpred-0.1.5.dist-info/RECORD
