Metadata-Version: 2.4
Name: mirnaprotpred
Version: 0.1.5
Summary: A package for miRNA protein prediction with SeqFinder and validator modules
Home-page: https://github.com/somenath-combio/mirnaprotpred
Author: Sudipta Sardar
Author-email: Sudipta Sardar <sudipta@pusan.ac.kr>
License: MIT
Project-URL: Homepage, https://github.com/somenath-combio/mirnaprotpred
Classifier: Programming Language :: Python :: 3
Classifier: License :: OSI Approved :: MIT License
Classifier: Operating System :: OS Independent
Requires-Python: >=3.13
License-File: LICENSE
Requires-Dist: pandas>=2.3.3
Requires-Dist: openpyxl>=3.1.5
Requires-Dist: biopython>=1.86
Requires-Dist: pyfiglet>=1.0.4
Requires-Dist: requests>=2.32.5
Requires-Dist: viennarna>=2.7.1
Dynamic: author
Dynamic: home-page
Dynamic: license-file
Dynamic: requires-python
